fabfed/__init__.py
fabfed/fabfed_manager.py
fabfed/controller/__init__.py
fabfed/controller/controller.py
fabfed/controller/helper.py
fabfed/controller/provider_factory.py
fabfed/exceptions/__init__.py
fabfed/model/__init__.py
fabfed/model/state.py
fabfed/policy/__init__.py
fabfed/policy/facility_port_handler.py
fabfed/policy/policy_helper.py
fabfed/policy/stitching_policy.json
fabfed/policy/stitching_policy_details.json
fabfed/policy/tag_handler.py
fabfed/provider/__init__.py
fabfed/provider/api/__init__.py
fabfed/provider/api/dependency_reslover.py
fabfed/provider/api/dependency_util.py
fabfed/provider/api/provider.py
fabfed/provider/api/resource_event_listener.py
fabfed/provider/aws/__init__.py
fabfed/provider/aws/aws_constants.py
fabfed/provider/aws/aws_exceptions.py
fabfed/provider/aws/aws_network.py
fabfed/provider/aws/aws_provider.py
fabfed/provider/aws/aws_utils.py
fabfed/provider/chi/__init__.py
fabfed/provider/chi/chi_constants.py
fabfed/provider/chi/chi_network.py
fabfed/provider/chi/chi_node.py
fabfed/provider/chi/chi_provider.py
fabfed/provider/chi/chi_util.py
fabfed/provider/cloudlab/__init__.py
fabfed/provider/cloudlab/cloudlab_constants.py
fabfed/provider/cloudlab/cloudlab_exceptions.py
fabfed/provider/cloudlab/cloudlab_network.py
fabfed/provider/cloudlab/cloudlab_node.py
fabfed/provider/cloudlab/cloudlab_provider.py
fabfed/provider/dummy/__init__.py
fabfed/provider/dummy/dummy_provider.py
fabfed/provider/fabric/__init__.py
fabfed/provider/fabric/fabric_constants.py
fabfed/provider/fabric/fabric_network.py
fabfed/provider/fabric/fabric_node.py
fabfed/provider/fabric/fabric_provider.py
fabfed/provider/fabric/fabric_slice.py
fabfed/provider/fabric/fabric_slice_helper.py
fabfed/provider/fabric/plugins.py
fabfed/provider/gcp/__init__.py
fabfed/provider/gcp/gcp_constants.py
fabfed/provider/gcp/gcp_exceptions.py
fabfed/provider/gcp/gcp_network.py
fabfed/provider/gcp/gcp_provider.py
fabfed/provider/gcp/gcp_utils.py
fabfed/provider/janus/__init__.py
fabfed_py-1.10.1.dist-info/LICENSE
fabfed_py-1.10.1.dist-info/METADATA
fabfed_py-1.10.1.dist-info/WHEEL
fabfed_py-1.10.1.dist-info/entry_points.txt
fabfed_py-1.10.1.dist-info/top_level.txt
fabfed_py-1.10.1.dist-info/RECORD
