Metadata-Version: 2.2
Name: fabfed-py
Version: 1.10.1
Summary: Fabfed Framework
Home-page: https://github.com/fabric-testbed/fabfed
Author: Abdelilah Essiari,Ezra Kissel,Liang Zhang
Author-email: aessiari@lbl.gov
Keywords: Fabfed Framework,Cloud,FABRIC,Chameleon,MOC
Classifier: Programming Language :: Python :: 3
Classifier: License :: OSI Approved :: MIT License
Classifier: Operating System :: OS Independent
Requires-Python: >=3.9
License-File: LICENSE
Requires-Dist: fabrictestbed-extensions
Requires-Dist: python-chi==0.17.11
Requires-Dist: sense-o-api==1.26
Requires-Dist: ansible==9.5.1
Requires-Dist: ansible-runner==2.3.6
Requires-Dist: xmltodict
Requires-Dist: boto3
Requires-Dist: google-cloud-compute
Dynamic: author
Dynamic: author-email
Dynamic: classifier
Dynamic: description
Dynamic: description-content-type
Dynamic: home-page
Dynamic: keywords
Dynamic: requires-dist
Dynamic: requires-python
Dynamic: summary
